timeseriesqualitycheck/__init__.py
timeseriesqualitycheck/signal_to_noise_ratio.py
timeseriesqualitycheck/timeseriesqualitycheck.py
timeseriesqualitycheck-0.0.3.dist-info/LICENSE
timeseriesqualitycheck-0.0.3.dist-info/METADATA
timeseriesqualitycheck-0.0.3.dist-info/WHEEL
timeseriesqualitycheck-0.0.3.dist-info/top_level.txt
timeseriesqualitycheck-0.0.3.dist-info/RECORD
