Metadata-Version: 2.1
Name: timeseriesqualitycheck
Version: 0.0.3
Summary: timeseriesqualitycheckis a Python package designed to assess the quality of time-series data. It provides a straightforward way to evaluate the integrity and cleanliness of time-series datasets by analyzing their Time Pattern Cohesion Score (TPCS) and Signal-to-Noise Ratio (SNR)
Home-page: https://github.com/karaposu/timeseriesqualitycheckis
Author: Enes
Author-email: enesesvetkuzucu@gmail.com
Project-URL: Bug Tracker, https://github.com/karaposu/timeseriesqualitycheckis/issues
Classifier: Programming Language :: Python :: 3
Classifier: License :: OSI Approved :: MIT License
Classifier: Operating System :: OS Independent
Requires-Python: >=3.6
License-File: LICENSE
Requires-Dist: numpy >=1.15.0
Requires-Dist: pandas >=1.15.0
Requires-Dist: sequentiality
Requires-Dist: tpcs
Requires-Dist: scipy
